threadly/Clock.py
threadly/Futures.py
threadly/KeyedExecutor.py
threadly/Scheduler.py
threadly/Structures.py
threadly/__init__.py
threadly-0.8.2.dist-info/LICENSES.txt
threadly-0.8.2.dist-info/METADATA
threadly-0.8.2.dist-info/WHEEL
threadly-0.8.2.dist-info/top_level.txt
threadly-0.8.2.dist-info/RECORD
