Metadata-Version: 2.1
Name: threadly
Version: 0.8.2
Summary: Thread pool and scheduler for python
Home-page: http://threadly.github.io/python-threadly/
Author: Luke Wahlmeier
Author-email: lwahlmeier@gmail.com
License: unlicense
Download-URL: https://github.com/threadly/python-threadly/tarball/0.8.2
Keywords: threading,scheduling
Platform: UNKNOWN
Classifier: Development Status :: 4 - Beta
Classifier: Intended Audience :: Developers
Classifier: Natural Language :: English
Classifier: Operating System :: MacOS :: MacOS X
Classifier: Operating System :: Microsoft :: Windows
Classifier: Operating System :: POSIX
Classifier: Operating System :: POSIX :: Linux
Classifier: Operating System :: Unix
Classifier: Programming Language :: Python
Classifier: Topic :: Software Development :: Libraries
Classifier: Topic :: Utilities
Classifier: License :: Public Domain
